README.rst
setup.py
sk_dist.egg-info/PKG-INFO
sk_dist.egg-info/SOURCES.txt
sk_dist.egg-info/dependency_links.txt
sk_dist.egg-info/requires.txt
sk_dist.egg-info/top_level.txt
skdist/__init__.py
skdist/postprocessing.py
skdist/preprocessing.py
skdist/distribute/__init__.py
skdist/distribute/_defaults.py
skdist/distribute/base.py
skdist/distribute/eliminate.py
skdist/distribute/encoder.py
skdist/distribute/ensemble.py
skdist/distribute/multiclass.py
skdist/distribute/predict.py
skdist/distribute/search.py
skdist/distribute/utils.py
skdist/distribute/validation.py
skdist/distribute/tests/__init__.py
skdist/distribute/tests/test_base.py
skdist/distribute/tests/test_defaults.py
skdist/distribute/tests/test_eliminate.py
skdist/distribute/tests/test_encoder.py
skdist/distribute/tests/test_ensemble.py
skdist/distribute/tests/test_init.py
skdist/distribute/tests/test_multiclass.py
skdist/distribute/tests/test_predict.py
skdist/distribute/tests/test_search.py
skdist/tests/__init__.py
skdist/tests/test_init.py
skdist/tests/test_postprocessing.py
skdist/tests/test_preprocessing.py
skdist/tests/test_spark.py