Metadata-Version: 2.1
Name: sk-dist
Version: 0.1.9
Summary: Distributed scikit-learn meta-estimators with PySpark
Home-page: UNKNOWN
Author: Ibotta Inc.
Author-email: machine_learning@ibotta.com
License: Apache 2.0
Download-URL: https://pypi.org/project/sk-dist/#files
Project-URL: Source Code, https://github.com/Ibotta/sk-dist
Platform: UNKNOWN
Classifier: Intended Audience :: Developers
Classifier: Programming Language :: Python
Classifier: Programming Language :: Python :: 3
Classifier: Programming Language :: Python :: 3.5
Classifier: Programming Language :: Python :: 3.6
Classifier: Programming Language :: Python :: 3.7
Classifier: Topic :: Scientific/Engineering
Requires-Python: >=3.5
Provides-Extra: tests
